chinois-0.2.2.dist-info/METADATA
chinois-0.2.2.dist-info/WHEEL
chinois-0.2.2.dist-info/licenses/LICENSE
chinois/.pytest_cache/.gitignore
chinois/.pytest_cache/CACHEDIR.TAG
chinois/.pytest_cache/README.md
chinois/.pytest_cache/v/cache/nodeids
chinois/.pytest_cache/v/cache/stepwise
chinois/__init__.py
chinois/css_match.py
chinois/css_parser.py
chinois/css_types.py
chinois/pretty.py
chinois/py.typed
chinois/util.py
chinois-0.2.2.dist-info/RECORD
