Metadata-Version: 2.1
Name: chinois
Version: 0.2.2
Summary: CSS selector implementation for Bisque and Campbells web scraping libraries.
Keywords: CSS HTML XML selector filter query soup
Author-Email: Louis Maddox <louismmx@gmail.com>
License: MIT
Classifier: Development Status :: 3 - Alpha
Classifier: Intended Audience :: Developers
Classifier: Natural Language :: English
Classifier: Topic :: Software Development :: Libraries
Classifier: Programming Language :: Python
Classifier: Programming Language :: Python :: 3.10
Classifier: Programming Language :: Python :: 3.11
Classifier: Topic :: Internet :: WWW/HTTP :: Dynamic Content
Classifier: Topic :: Text Processing :: Markup :: HTML
Classifier: Topic :: Text Processing :: Markup :: SGML
Classifier: Topic :: Text Processing :: Markup :: XML
Project-URL: Homepage, https://github.com/lmmx/chinois
Project-URL: Repository, https://github.com/lmmx/chinois.git
Requires-Python: >=3.10
Provides-Extra: campbells
Provides-Extra: bisque
Provides-Extra: html5lib
Provides-Extra: lxml
Requires-Dist: campbells>=0.2.0; extra == "campbells"
Requires-Dist: bisque>=0.1.1; extra == "bisque"
Requires-Dist: html5lib>=1.1; extra == "html5lib"
Requires-Dist: lxml>=4.9.3; extra == "lxml"
